tartiflette-1.4.1.dist-info/METADATA
tartiflette-1.4.1.dist-info/RECORD
tartiflette-1.4.1.dist-info/LICENSE
tartiflette-1.4.1.dist-info/WHEEL
tartiflette-1.4.1.dist-info/top_level.txt
tartiflette/__init__.py
tartiflette/engine.py
tartiflette/py.typed
tartiflette/types/argument.py
tartiflette/types/enum.py
tartiflette/types/directive.py
tartiflette/types/input_field.py
tartiflette/types/input_object.py
tartiflette/types/schema_extension.py
tartiflette/types/interface.py
tartiflette/types/__init__.py
tartiflette/types/type.py
tartiflette/types/scalar.py
tartiflette/types/union.py
tartiflette/types/object.py
tartiflette/types/field.py
tartiflette/types/list.py
tartiflette/types/non_null.py
tartiflette/types/helpers/get_directive_instances.py
tartiflette/types/helpers/__init__.py
tartiflette/types/helpers/type.py
tartiflette/types/helpers/reduce_type.py
tartiflette/types/helpers/definition.py
tartiflette/types/exceptions/__init__.py
tartiflette/types/exceptions/tartiflette.py
tartiflette/utils/__init__.py
tartiflette/utils/errors.py
tartiflette/utils/callables.py
tartiflette/utils/type_from_ast.py
tartiflette/utils/values.py
tartiflette/utils/directives.py
tartiflette/constants/__init__.py
tartiflette/constants/values.py
tartiflette/directive/directive.py
tartiflette/directive/__init__.py
tartiflette/directive/builtins/skip.py
tartiflette/directive/builtins/include.py
tartiflette/directive/builtins/__init__.py
tartiflette/directive/builtins/deprecated.py
tartiflette/directive/builtins/non_introspectable.py
tartiflette/subscription/__init__.py
tartiflette/subscription/subscription.py
tartiflette/scalar/__init__.py
tartiflette/scalar/scalar.py
tartiflette/scalar/builtins/boolean.py
tartiflette/scalar/builtins/time.py
tartiflette/scalar/builtins/__init__.py
tartiflette/scalar/builtins/date.py
tartiflette/scalar/builtins/string.py
tartiflette/scalar/builtins/id.py
tartiflette/scalar/builtins/float.py
tartiflette/scalar/builtins/datetime.py
tartiflette/scalar/builtins/int.py
tartiflette/schema/__init__.py
tartiflette/schema/registry.py
tartiflette/schema/schema.py
tartiflette/schema/bakery.py
