Metadata-Version: 2.1
Name: tartiflette
Version: 1.4.1
Summary: GraphQL Engine for Python
Home-page: https://tartiflette.io
Author: Dailymotion Core API Team
Author-email: team@tartiflette.io
License: MIT
Project-URL: Documentation, https://tartiflette.io
Project-URL: Source code, https://github.com/tartiflette/tartiflette
Project-URL: Changelog, https://github.com/tartiflette/tartiflette/blob/master/CHANGELOG.md
Project-URL: Issue tracker, https://github.com/tartiflette/tartiflette/issues
Keywords: api,graphql,protocol,rest,relay,tartiflette,dailymotion
Platform: UNKNOWN
Classifier: Intended Audience :: Developers
Classifier: Topic :: Software Development :: Libraries
Classifier: Programming Language :: Python :: 3.6
Classifier: Programming Language :: Python :: 3.7
Classifier: Programming Language :: Python :: 3.8
Classifier: Programming Language :: Python :: 3.9
Classifier: Programming Language :: Python :: 3.10
Classifier: Programming Language :: Python :: Implementation :: CPython
Classifier: Programming Language :: Python :: Implementation :: PyPy
Requires-Python: >=3.6
License-File: LICENSE
Requires-Dist: cffi (<2.0.0,>=1.0.0)
Requires-Dist: lark-parser (==0.12.0)
Provides-Extra: benchmark
Requires-Dist: pytest-benchmark (==3.4.1) ; extra == 'benchmark'
Provides-Extra: test
Requires-Dist: pytest (==6.2.5) ; extra == 'test'
Requires-Dist: pytest-cov (==3.0.0) ; extra == 'test'
Requires-Dist: pytest-asyncio (==0.16.0) ; extra == 'test'
Requires-Dist: pytest-xdist (==2.4.0) ; extra == 'test'
Requires-Dist: pylint (==2.11.1) ; extra == 'test'
Requires-Dist: black (==21.8b0) ; extra == 'test'
Requires-Dist: isort (==5.10.1) ; extra == 'test'
